<?xml version="1.0" encoding="UTF-8" ?>
<Configuration>
  <WMS>
    <TitleFont location="{ADAGUC_PATH}/data/fonts/FreeSans.ttf" size="19"/>
    <SubTitleFont location="{ADAGUC_PATH}/data/fonts/FreeSans.ttf" size="19"/>
    <DimensionFont location="{ADAGUC_PATH}/data/fonts/FreeSans.ttf" size="7"/>
    <ContourFont location="{ADAGUC_PATH}/data/fonts/Roboto-Light.ttf" size="8.6"/>
    <LegendFont location="{ADAGUC_PATH}/data/fonts/OpenSans-Regular.ttf" size="9"/>
    <GridFont location="{ADAGUC_PATH}/data/fonts/FreeSans.ttf" size="5"/>
  </WMS>
</Configuration>